nonebot_plugin_picmcstat/__init__.py
nonebot_plugin_picmcstat/__main__.py
nonebot_plugin_picmcstat/config.py
nonebot_plugin_picmcstat/const.py
nonebot_plugin_picmcstat/draw.py
nonebot_plugin_picmcstat/res.py
nonebot_plugin_picmcstat/util.py
nonebot_plugin_picmcstat/res/default.png
nonebot_plugin_picmcstat/res/dirt.png
nonebot_plugin_picmcstat/res/grass_side_carried.png
nonebot_plugin_picmcstat-0.8.1.dist-info/METADATA
nonebot_plugin_picmcstat-0.8.1.dist-info/WHEEL
nonebot_plugin_picmcstat-0.8.1.dist-info/licenses/LICENSE
nonebot_plugin_picmcstat-0.8.1.dist-info/RECORD
