Metadata-Version: 2.4
Name: nonebot-plugin-picmcstat
Version: 0.8.1
Summary: A NoneBot2 plugin generates a pic from a Minecraft server's MOTD
Project-URL: homepage, https://github.com/lgc-NB2Dev/nonebot-plugin-picmcstat
Author-email: LgCookie <lgc2333@126.com>
License: MIT
License-File: LICENSE
Requires-Python: <4.0,>=3.10
Requires-Dist: cookit[pydantic]>=0.13.0
Requires-Dist: dnspython>=2.7.0
Requires-Dist: mcstatus>=12.0.5
Requires-Dist: nonebot-plugin-alconna>=0.59.4
Requires-Dist: nonebot2>=2.4.3
Requires-Dist: pil-utils>=0.2.2
Requires-Dist: punycode>=0.2.1
